certbot_httpreq/__init__.py
certbot_httpreq/authenticator.py
certbot_httpreq/installer.py
certbot_httpreq-0.0.19.data/data/share/certbot-httpreq/etc/letsencrypt/certbot-httpreq.yml
certbot_httpreq-0.0.19.dist-info/LICENSE
certbot_httpreq-0.0.19.dist-info/METADATA
certbot_httpreq-0.0.19.dist-info/WHEEL
certbot_httpreq-0.0.19.dist-info/entry_points.txt
certbot_httpreq-0.0.19.dist-info/top_level.txt
certbot_httpreq-0.0.19.dist-info/RECORD
